fluidattacks_core_test/authz/__init__.py
fluidattacks_core_test/authz/py.typed
fluidattacks_core_test/authz/types.py
fluidattacks_core_test-0.1.2.dist-info/METADATA
fluidattacks_core_test-0.1.2.dist-info/WHEEL
fluidattacks_core_test-0.1.2.dist-info/RECORD
