Metadata-Version: 2.1
Name: fluidattacks-core-test
Version: 0.1.2
Summary: Fluid Attacks Core Library Test
License: MPL-2.0
Author: Development
Author-email: development@fluidattacks.com
Requires-Python: >=3.11,<4.0
Classifier: License :: OSI Approved
Classifier: Programming Language :: Python :: 3
Classifier: Programming Language :: Python :: 3.11
Classifier: Programming Language :: Python :: 3.12
